pyMSA_plot/__init__.py
pyMSA_plot/functions.py
pymsa_plot-0.0.1.dist-info/METADATA
pymsa_plot-0.0.1.dist-info/WHEEL
pymsa_plot-0.0.1.dist-info/licenses/LICENSE
pymsa_plot-0.0.1.dist-info/RECORD
