Metadata-Version: 2.1
Name: pyMSA_plot
Version: 0.0.1
Summary: A package to plot MSA
Project-URL: Homepage, https://github.com/Khalimat/pyMSA_plot
Project-URL: Bug Tracker, https://github.com/Khalimat/pyMSA_plot/issues
Author-email: "Khalimat A. Murtazalieva" <kam@ebi.ac.uk>
License: Copyright (c) 2018 The Python Packaging Authority
Classifier: License :: OSI Approved :: MIT License
Classifier: Operating System :: OS Independent
Classifier: Programming Language :: Python :: 3
Requires-Python: >=3.8
